uiadmin_flask/CoreController.py
uiadmin_flask/Uiadmin.py
uiadmin_flask/__init__.py
uiadmin_flask/utils.py
uiadmin_flask/util/__init__.py
uiadmin_flask/util/xybuilder/XyBuilderForm.py
uiadmin_flask/util/xybuilder/XyBuilderList.py
uiadmin_flask/util/xybuilder/__init__.py
Uiadmin_Flask-1.0.7.dist-info/LICENSE.md
Uiadmin_Flask-1.0.7.dist-info/METADATA
Uiadmin_Flask-1.0.7.dist-info/WHEEL
Uiadmin_Flask-1.0.7.dist-info/top_level.txt
Uiadmin_Flask-1.0.7.dist-info/RECORD
